[
  {
    "questionText": "What is the capital of France?",
    "optionA": "Berlin",
    "optionB": "Madrid",
    "optionC": "Paris",
    "optionD": "Rome",
    "correctOption": "C"
  },
  {
    "questionText": "Which planet is known as the Red Planet?",
    "optionA": "Earth",
    "optionB": "Mars",
    "optionC": "Jupiter",
    "optionD": "Venus",
    "correctOption": "B"
  },
  {
    "questionText": "What is the largest mammal?",
    "optionA": "Elephant",
    "optionB": "Blue Whale",
    "optionC": "Giraffe",
    "optionD": "Shark",
    "correctOption": "B"
  },
  {
    "questionText": "Who wrote 'Macbeth'?",
    "optionA": "Shakespeare",
    "optionB": "Dickens",
    "optionC": "Austen",
    "optionD": "Hemingway",
    "correctOption": "A"
  },
  {
    "questionText": "What is the chemical symbol for water?",
    "optionA": "O2",
    "optionB": "H2O",
    "optionC": "CO2",
    "optionD": "NaCl",
    "correctOption": "B"
  },
  {
    "questionText": "What is the largest ocean on Earth?",
    "optionA": "Atlantic Ocean",
    "optionB": "Indian Ocean",
    "optionC": "Pacific Ocean",
    "optionD": "Arctic Ocean",
    "correctOption": "C"
  },
  {
    "questionText": "Who painted the Mona Lisa?",
    "optionA": "Picasso",
    "optionB": "Van Gogh",
    "optionC": "Da Vinci",
    "optionD": "Michelangelo",
    "correctOption": "C"
  },
  {
    "questionText": "What is the square root of 64?",
    "optionA": "6",
    "optionB": "8",
    "optionC": "10",
    "optionD": "12",
    "correctOption": "B"
  },
  {
    "questionText": "What is the smallest prime number?",
    "optionA": "1",
    "optionB": "2",
    "optionC": "3",
    "optionD": "5",
    "correctOption": "B"
  },
  {
    "questionText": "What is the largest country by area?",
    "optionA": "Canada",
    "optionB": "United States",
    "optionC": "Russia",
    "optionD": "China",
    "correctOption": "C"
  }
]
